{
  "jamboards": [
    {
      "id": "1",
      "name": "",
      "elements": [],
      "comments": [
        {
          "author": "Hooman",
          "avatar": "https://avatars.githubusercontent.com/u/10214025?v=4",
          "id": "1",
          "content": "asanas",
          "datetime": "2024-08-07T13:15:33.975Z"
        }
      ],
      "users": [],
      "isLoading": false
    }
  ],
  "elements": [
    {
      "id": "891fbe77-d259-42df-ab69-26ffca0e1140",
      "appearence": {},
      "content": {
        "title": "Title",
        "text": "create and change elemetns real time",
        "imageUrl": "url"
      },
      "info": {},
      "type": "note",
      "size": {
        "width": 414,
        "height": 417,
        "isBeingResized": false
      },
      "position": {
        "x": 310,
        "y": 119,
        "isBeingDragged": false
      },
      "status": "",
      "options": {}
    },
    {
      "id": "f9de1339-692a-40cc-b7fb-80a9dbd31a11",
      "appearence": {},
      "content": {
        "title": "Title",
        "text": "Double click to change",
        "imageUrl": "url"
      },
      "info": {},
      "type": "button",
      "size": {
        "width": 199,
        "height": 200,
        "isBeingResized": false
      },
      "position": {
        "x": 940,
        "y": 481,
        "isBeingDragged": false
      },
      "status": "",
      "options": {}
    },
    {
      "id": "92531091-0e8f-4b94-87d2-4318360a3d41",
      "appearence": {},
      "content": {
        "title": "Title",
        "text": "see other browsers real time",
        "imageUrl": "url"
      },
      "info": {},
      "type": "tag",
      "size": {
        "width": 200,
        "height": 200,
        "isBeingResized": false
      },
      "position": {
        "x": 887,
        "y": 191,
        "isBeingDragged": false
      },
      "status": "",
      "options": {}
    },
    {
      "id": "4afd2f5e-f64e-4276-8651-3eba293374ab",
      "appearence": {},
      "content": {
        "title": "Title",
        "text": "This is a new element",
        "imageUrl": "url"
      },
      "info": {
        "createAt": "2024-08-13T11:10:33.598Z",
        "modifiedAt": "2024-08-13T11:10:33.598Z",
        "createdBy": {},
        "modifiedBy": {}
      },
      "type": "tag",
      "size": {
        "width": 200,
        "height": 200,
        "isBeingResized": false
      },
      "position": {
        "x": 708,
        "y": 512,
        "isBeingDragged": false
      },
      "status": "",
      "options": {}
    }
  ],
  "users": [
    {
      "id": "1",
      "name": "Hooman",
      "status": "online",
      "avatarUrl": "https://avatars.githubusercontent.com/u/10214025?v=4",
      "curser": {
        "position": {
          "x": 500,
          "y": 400,
          "moduleName": "jamboard",
          "projectId": "1"
        },
        "actions": "move",
        "color": "#207fc9"
      },
      "activeModule": "planning"
    },
    {
      "id": "2",
      "name": "luke skywalker",
      "status": "offline",
      "avatarUrl": "https://avatars.githubusercontent.com/u/10214021?v=4",
      "curser": {
        "position": {
          "x": 400,
          "y": 500,
          "moduleName": "design",
          "projectId": "1"
        },
        "actions": "move",
        "color": "#32a852"
      },
      "activeModule": "planning"
    },
    {
      "id": "3",
      "name": "Elton John",
      "status": "offline",
      "avatarUrl": "https://avatars.githubusercontent.com/u/10214027?v=4",
      "curser": {
        "position": {
          "x": 400,
          "y": 500,
          "moduleName": "planning",
          "projectId": "1"
        },
        "actions": "move",
        "color": "#e62e2e"
      },
      "activeModule": "planning"
    },
    {
      "id": "4",
      "name": "Austin Burris",
      "status": "offline",
      "avatarUrl": "https://avatars.githubusercontent.com/u/10214029?v=4",
      "curser": {
        "position": {
          "x": 400,
          "y": 500,
          "moduleName": "jamboard",
          "projectId": "1"
        },
        "actions": "move",
        "color": "#1c750b"
      },
      "activeModule": "planning"
    }
  ],
  "comments": [
    {
      "author": "Hooman",
      "avatar": "https://avatars.githubusercontent.com/u/10214025?v=4",
      "id": "1",
      "content": "asas",
      "datetime": "2024-08-07T11:49:18.049Z",
      "position": {
        "x": 400,
        "y": 500
      }
    },
    {
      "author": "luke skywalker",
      "avatar": "https://avatars.githubusercontent.com/u/10214021?v=4",
      "id": "2",
      "content": "asanas",
      "datetime": "2024-08-07T13:15:33.975Z",
      "position": {
        "x": 200,
        "y": 300
      }
    },
    {
      "id": "0317"
    },
    {
      "id": "5534"
    },
    {
      "id": "6880"
    },
    {
      "id": "4111"
    }
  ]
}